tuskvector/__init__.py
tuskvector/api_key_service.py
tuskvector/database.py
tuskvector/embeddings_router.py
tuskvector/items_router.py
tuskvector/llm_router.py
tuskvector/main.py
tuskvector/rate_limiter.py
tuskvector/schemas.py
tuskvector-1.0.1.dist-info/METADATA
tuskvector-1.0.1.dist-info/WHEEL
tuskvector-1.0.1.dist-info/top_level.txt
tuskvector-1.0.1.dist-info/RECORD
