Metadata-Version: 2.1
Name: tuskvector
Version: 1.0.1
Summary: TuskVector API Platform
Author-email: Niklas <api.tuskvector@gmail.com>
License: MIT
Requires-Python: >=3.8
Requires-Dist: fastapi
Requires-Dist: sqlalchemy
Requires-Dist: pgvector
Requires-Dist: python-dotenv
Requires-Dist: openai
Requires-Dist: pydantic
Provides-Extra: dev
Requires-Dist: pytest ; extra == 'dev'
